MANIFEST.in
README.md
pyproject.toml
setup.cfg
setup.py
pNbody/Mkgmov.py
pNbody/Movie.py
pNbody/__init__.py
pNbody/_transformations.py
pNbody/arrays_manager.py
pNbody/cooling.py
pNbody/cosmo.py
pNbody/ctes.py
pNbody/eos.py
pNbody/errorfuncs.py
pNbody/fortranfile.py
pNbody/fourier.py
pNbody/geometry.py
pNbody/h5utils.py
pNbody/ic.py
pNbody/interpolator.py
pNbody/iofunc.py
pNbody/kernels.py
pNbody/lazy_loading.py
pNbody/libdisk.py
pNbody/libgrid.py
pNbody/liblog.py
pNbody/libmiyamoto.py
pNbody/libqt.py
pNbody/libutil.py
pNbody/main.py
pNbody/message.py
pNbody/mpiwrapper.py
pNbody/observations.py
pNbody/palette.py
pNbody/param.py
pNbody/parameters.py
pNbody/phot.py
pNbody/profiles.py
pNbody/system.py
pNbody/talkgdisp.py
pNbody/thermodyn.py
pNbody/units.py
pNbody.egg-info/PKG-INFO
pNbody.egg-info/SOURCES.txt
pNbody.egg-info/dependency_links.txt
pNbody.egg-info/requires.txt
pNbody.egg-info/top_level.txt
pNbody/Cosmology/__init__.py
pNbody/Cosmology/cosmicpy.py
pNbody/DF/__init__.py
pNbody/IMF/__init__.py
pNbody/Isochrones/BastI.py
pNbody/Isochrones/CMD.py
pNbody/Isochrones/MIST.py
pNbody/Isochrones/__init__.py
pNbody/Isochrones/main.py
pNbody/Mockimgs/__init__.py
pNbody/Mockimgs/ccd.py
pNbody/Mockimgs/detector.py
pNbody/Mockimgs/dzone.py
pNbody/Mockimgs/filters.py
pNbody/Mockimgs/ifu.py
pNbody/Mockimgs/instrument.py
pNbody/Mockimgs/lib.py
pNbody/Mockimgs/los.py
pNbody/Mockimgs/luminosities.py
pNbody/Mockimgs/mos.py
pNbody/Mockimgs/noise.py
pNbody/Mockimgs/obs_object.py
pNbody/Mockimgs/parameters.py
pNbody/Mockimgs/scoords.py
pNbody/Mockimgs/spectra.py
pNbody/Mockimgs/spoints.py
pNbody/Mockimgs/telescope.py
pNbody/Mockimgs/utils.py
pNbody/RT/__init__.py
pNbody/RT/blackbody.py
pNbody/SSP/__init__.py
pNbody/SSP/libRGBs.py
pNbody/SSP/libSSPluminosity.py
pNbody/SSP/libbastitime.py
pNbody/SSP/libbruzual.py
pNbody/SSP/libmaraston.py
pNbody/SSP/libtill.py
pNbody/SSP/libvazdekis.py
pNbody/config/defaultparameters
pNbody/config/unitsparameters
pNbody/config/extensions/default_extension.py
pNbody/config/extensions/gear.py
pNbody/config/formats/arepo.py
pNbody/config/formats/auriga.py
pNbody/config/formats/coco.py
