Metadata-Version: 2.1
Name: pNbody
Version: 5.0.10
Summary: This module provides lots of tools used
Home-page: http://obswww.unige.ch/~revaz/pNbody/index.html
Author: Yves Revaz
Author-email: yves.revaz@epfl.ch
License: GPLv3
Platform: UNKNOWN
